{
  "strategyName": "Ex15",
  "projectName": "2-1",
  "maxPathsPerProject": 32,
  "totals": {
    "states": 129,
    "transitions": 221
  },
  "points": [
    {
      "pathCount": 1,
      "coveredStates": 25,
      "stateCoverageRatio": 0.1937984496124031,
      "coveredTransitions": 25,
      "transitionCoverageRatio": 0.11312217194570136
    },
    {
      "pathCount": 2,
      "coveredStates": 40,
      "stateCoverageRatio": 0.31007751937984496,
      "coveredTransitions": 41,
      "transitionCoverageRatio": 0.18552036199095023
    },
    {
      "pathCount": 3,
      "coveredStates": 47,
      "stateCoverageRatio": 0.3643410852713178,
      "coveredTransitions": 50,
      "transitionCoverageRatio": 0.22624434389140272
    },
    {
      "pathCount": 4,
      "coveredStates": 54,
      "stateCoverageRatio": 0.4186046511627907,
      "coveredTransitions": 58,
      "transitionCoverageRatio": 0.26244343891402716
    },
    {
      "pathCount": 5,
      "coveredStates": 60,
      "stateCoverageRatio": 0.46511627906976744,
      "coveredTransitions": 64,
      "transitionCoverageRatio": 0.2895927601809955
    },
    {
      "pathCount": 6,
      "coveredStates": 66,
      "stateCoverageRatio": 0.5116279069767442,
      "coveredTransitions": 70,
      "transitionCoverageRatio": 0.3167420814479638
    },
    {
      "pathCount": 7,
      "coveredStates": 71,
      "stateCoverageRatio": 0.5503875968992248,
      "coveredTransitions": 76,
      "transitionCoverageRatio": 0.3438914027149321
    },
    {
      "pathCount": 8,
      "coveredStates": 77,
      "stateCoverageRatio": 0.5968992248062015,
      "coveredTransitions": 82,
      "transitionCoverageRatio": 0.37104072398190047
    },
    {
      "pathCount": 9,
      "coveredStates": 80,
      "stateCoverageRatio": 0.6201550387596899,
      "coveredTransitions": 86,
      "transitionCoverageRatio": 0.3891402714932127
    },
    {
      "pathCount": 10,
      "coveredStates": 83,
      "stateCoverageRatio": 0.6434108527131783,
      "coveredTransitions": 90,
      "transitionCoverageRatio": 0.4072398190045249
    },
    {
      "pathCount": 11,
      "coveredStates": 85,
      "stateCoverageRatio": 0.6589147286821705,
      "coveredTransitions": 94,
      "transitionCoverageRatio": 0.4253393665158371
    },
    {
      "pathCount": 12,
      "coveredStates": 87,
      "stateCoverageRatio": 0.6744186046511628,
      "coveredTransitions": 98,
      "transitionCoverageRatio": 0.4434389140271493
    },
    {
      "pathCount": 13,
      "coveredStates": 88,
      "stateCoverageRatio": 0.6821705426356589,
      "coveredTransitions": 102,
      "transitionCoverageRatio": 0.46153846153846156
    },
    {
      "pathCount": 14,
      "coveredStates": 89,
      "stateCoverageRatio": 0.689922480620155,
      "coveredTransitions": 106,
      "transitionCoverageRatio": 0.4796380090497738
    },
    {
      "pathCount": 15,
      "coveredStates": 91,
      "stateCoverageRatio": 0.7054263565891473,
      "coveredTransitions": 109,
      "transitionCoverageRatio": 0.49321266968325794
    },
    {
      "pathCount": 16,
      "coveredStates": 93,
      "stateCoverageRatio": 0.7209302325581395,
      "coveredTransitions": 112,
      "transitionCoverageRatio": 0.5067873303167421
    },
    {
      "pathCount": 17,
      "coveredStates": 94,
      "stateCoverageRatio": 0.7286821705426356,
      "coveredTransitions": 115,
      "transitionCoverageRatio": 0.5203619909502263
    },
    {
      "pathCount": 18,
      "coveredStates": 95,
      "stateCoverageRatio": 0.7364341085271318,
      "coveredTransitions": 118,
      "transitionCoverageRatio": 0.5339366515837104
    },
    {
      "pathCount": 19,
      "coveredStates": 96,
      "stateCoverageRatio": 0.7441860465116279,
      "coveredTransitions": 121,
      "transitionCoverageRatio": 0.5475113122171946
    },
    {
      "pathCount": 20,
      "coveredStates": 97,
      "stateCoverageRatio": 0.751937984496124,
      "coveredTransitions": 124,
      "transitionCoverageRatio": 0.5610859728506787
    },
    {
      "pathCount": 21,
      "coveredStates": 97,
      "stateCoverageRatio": 0.751937984496124,
      "coveredTransitions": 127,
      "transitionCoverageRatio": 0.5746606334841629
    },
    {
      "pathCount": 22,
      "coveredStates": 98,
      "stateCoverageRatio": 0.7596899224806202,
      "coveredTransitions": 129,
      "transitionCoverageRatio": 0.583710407239819
    },
    {
      "pathCount": 23,
      "coveredStates": 99,
      "stateCoverageRatio": 0.7674418604651163,
      "coveredTransitions": 131,
      "transitionCoverageRatio": 0.5927601809954751
    },
    {
      "pathCount": 24,
      "coveredStates": 100,
      "stateCoverageRatio": 0.7751937984496124,
      "coveredTransitions": 133,
      "transitionCoverageRatio": 0.6018099547511312
    },
    {
      "pathCount": 25,
      "coveredStates": 101,
      "stateCoverageRatio": 0.7829457364341085,
      "coveredTransitions": 135,
      "transitionCoverageRatio": 0.6108597285067874
    },
    {
      "pathCount": 26,
      "coveredStates": 102,
      "stateCoverageRatio": 0.7906976744186046,
      "coveredTransitions": 137,
      "transitionCoverageRatio": 0.6199095022624435
    },
    {
      "pathCount": 27,
      "coveredStates": 103,
      "stateCoverageRatio": 0.7984496124031008,
      "coveredTransitions": 139,
      "transitionCoverageRatio": 0.6289592760180995
    },
    {
      "pathCount": 28,
      "coveredStates": 104,
      "stateCoverageRatio": 0.8062015503875969,
      "coveredTransitions": 141,
      "transitionCoverageRatio": 0.6380090497737556
    },
    {
      "pathCount": 29,
      "coveredStates": 105,
      "stateCoverageRatio": 0.813953488372093,
      "coveredTransitions": 143,
      "transitionCoverageRatio": 0.6470588235294118
    },
    {
      "pathCount": 30,
      "coveredStates": 106,
      "stateCoverageRatio": 0.8217054263565892,
      "coveredTransitions": 145,
      "transitionCoverageRatio": 0.6561085972850679
    },
    {
      "pathCount": 31,
      "coveredStates": 107,
      "stateCoverageRatio": 0.8294573643410853,
      "coveredTransitions": 147,
      "transitionCoverageRatio": 0.665158371040724
    },
    {
      "pathCount": 32,
      "coveredStates": 108,
      "stateCoverageRatio": 0.8372093023255814,
      "coveredTransitions": 149,
      "transitionCoverageRatio": 0.6742081447963801
    }
  ]
}